YouHaveTooMuchShit/README.md
YouHaveTooMuchShit/__init__.py
YouHaveTooMuchShit/__main__.py
YouHaveTooMuchShit/file.epub
YouHaveTooMuchShit/index.html
YouHaveTooMuchShit/css/__init__.py
YouHaveTooMuchShit/css/annotations.css
YouHaveTooMuchShit/css/main.css
YouHaveTooMuchShit/css/normalize.css
YouHaveTooMuchShit/css/popup.css
YouHaveTooMuchShit/font/__init__.py
YouHaveTooMuchShit/font/fontello.eot
YouHaveTooMuchShit/font/fontello.svg
YouHaveTooMuchShit/font/fontello.ttf
YouHaveTooMuchShit/font/fontello.woff
YouHaveTooMuchShit/img/__init__.py
YouHaveTooMuchShit/img/annotator-glyph-sprite.png
YouHaveTooMuchShit/img/annotator-icon-sprite.png
YouHaveTooMuchShit/img/apple-touch-icon.png
YouHaveTooMuchShit/img/cancelfullscreen.png
YouHaveTooMuchShit/img/close.png
YouHaveTooMuchShit/img/fullscreen.png
YouHaveTooMuchShit/img/loader.gif
YouHaveTooMuchShit/img/menu-icon.png
YouHaveTooMuchShit/img/save.png
YouHaveTooMuchShit/img/saved.png
YouHaveTooMuchShit/img/settings-s.png
YouHaveTooMuchShit/img/settings.png
YouHaveTooMuchShit/img/star.png
YouHaveTooMuchShit/js/__init__.py
YouHaveTooMuchShit/js/epub.js
YouHaveTooMuchShit/js/epub.min.js
YouHaveTooMuchShit/js/epub.min.map
YouHaveTooMuchShit/js/hooks.min.js
YouHaveTooMuchShit/js/hooks.min.map
YouHaveTooMuchShit/js/reader.js
YouHaveTooMuchShit/js/reader.js.map
YouHaveTooMuchShit/js/reader.min.js
YouHaveTooMuchShit/js/reader.min.map
YouHaveTooMuchShit/js/hooks/__init__.py
YouHaveTooMuchShit/js/hooks/extensions/__init__.py
YouHaveTooMuchShit/js/hooks/extensions/highlight.js
YouHaveTooMuchShit/js/libs/__init__.py
YouHaveTooMuchShit/js/libs/jquery.min.js
YouHaveTooMuchShit/js/libs/localforage.min.js
YouHaveTooMuchShit/js/libs/screenfull.js
YouHaveTooMuchShit/js/libs/screenfull.min.js
YouHaveTooMuchShit/js/libs/zip.min.js
YouHaveTooMuchShit/js/plugins/__init__.py
YouHaveTooMuchShit/js/plugins/hypothesis.js
YouHaveTooMuchShit/js/plugins/search.js
you_have_too_much_shit-2024.3.2.0.dist-info/METADATA
you_have_too_much_shit-2024.3.2.0.dist-info/WHEEL
you_have_too_much_shit-2024.3.2.0.dist-info/entry_points.txt
you_have_too_much_shit-2024.3.2.0.dist-info/top_level.txt
you_have_too_much_shit-2024.3.2.0.dist-info/RECORD
